storages/__init__.py
storages/base.py
storages/compress.py
storages/utils.py
storages/backends/__init__.py
storages/backends/apache_libcloud.py
storages/backends/azure_storage.py
storages/backends/dropbox.py
storages/backends/ftp.py
storages/backends/gcloud.py
storages/backends/s3.py
storages/backends/s3boto3.py
storages/backends/sftpstorage.py
django_storages_alt-1.14.2.dist-info/LICENSE
django_storages_alt-1.14.2.dist-info/METADATA
django_storages_alt-1.14.2.dist-info/WHEEL
django_storages_alt-1.14.2.dist-info/top_level.txt
django_storages_alt-1.14.2.dist-info/RECORD
