Metadata-Version: 2.1
Name: django-storages-alt
Version: 1.14.2
Summary: Support for many storage backends in Django
Author-email: Rohan Phulkar <rohanphulkar936@gmail.com>
License: BSD-3-Clause
Project-URL: Homepage, https://github.com/rohanphulkar/django-storages
Classifier: Development Status :: 5 - Production/Stable
Classifier: Environment :: Web Environment
Classifier: Framework :: Django
Classifier: Framework :: Django :: 3.2
Classifier: Framework :: Django :: 4.1
Classifier: Framework :: Django :: 4.2
Classifier: Intended Audience :: Developers
Classifier: License :: OSI Approved :: BSD License
Classifier: Operating System :: OS Independent
Classifier: Programming Language :: Python
Classifier: Programming Language :: Python :: 3 :: Only
Classifier: Programming Language :: Python :: 3.7
Classifier: Programming Language :: Python :: 3.8
Classifier: Programming Language :: Python :: 3.9
Classifier: Programming Language :: Python :: 3.10
Classifier: Programming Language :: Python :: 3.11
Requires-Python: >=3.7
License-File: LICENSE
Requires-Dist: Django>=3.2
Provides-Extra: azure
Requires-Dist: azure-core>=1.13; extra == "azure"
Requires-Dist: azure-storage-blob>=12; extra == "azure"
Provides-Extra: boto3
Requires-Dist: boto3>=1.4.4; extra == "boto3"
Provides-Extra: dropbox
Requires-Dist: dropbox>=7.2.1; extra == "dropbox"
Provides-Extra: google
Requires-Dist: google-cloud-storage>=1.27; extra == "google"
Provides-Extra: libcloud
Requires-Dist: apache-libcloud; extra == "libcloud"
Provides-Extra: s3
Requires-Dist: boto3>=1.4.4; extra == "s3"
Provides-Extra: sftp
Requires-Dist: paramiko>=1.15; extra == "sftp"
